pymelcloud/__init__.py
pymelcloud/ata_device.py
pymelcloud/atw_device.py
pymelcloud/client.py
pymelcloud/const.py
pymelcloud/device.py
pymelcloud/erv_device.py
python_melcloud-0.1.0.dist-info/LICENSE.md
python_melcloud-0.1.0.dist-info/METADATA
python_melcloud-0.1.0.dist-info/WHEEL
python_melcloud-0.1.0.dist-info/RECORD
