Metadata-Version: 2.3
Name: python-melcloud
Version: 0.1.0
Summary: Asynchronous Python client for controlling Melcloud devices.
License: MIT
Keywords: melcloud,homeassistant,api,async,client
Author: Erwin Douna
Author-email: e.douna@gmail.com
Maintainer: Erwin Douna
Maintainer-email: e.douna@gmail.com
Requires-Python: >=3.12,<4.0
Classifier: Development Status :: 5 - Production/Stable
Classifier: Framework :: AsyncIO
Classifier: Intended Audience :: Developers
Classifier: License :: OSI Approved :: MIT License
Classifier: Natural Language :: English
Classifier: Programming Language :: Python :: 3
Classifier: Programming Language :: Python :: 3.12
Classifier: Programming Language :: Python :: 3.13
Classifier: Topic :: Software Development :: Libraries :: Python Modules
Requires-Dist: aiohttp (>=3.0.0)
Requires-Dist: aioresponses (>=0.7.6,<0.8.0)
Requires-Dist: mashumaro (>=3.10)
Requires-Dist: orjson (>=3.9.8)
Requires-Dist: yarl (>=1.6.0)
Project-URL: Bug Tracker, https://github.com/erwindouna/python-melcloud/issues
Project-URL: Changelog, https://github.com/erwindouna/python-melcloud/releases
Project-URL: Documentation, https://github.com/erwindouna/python-melcloud
Project-URL: Homepage, https://github.com/erwindouna/python-melcloud
Project-URL: Repository, https://github.com/erwindouna/python-melcloud
